Undo_Redo/__init__.py
Undo_Redo-1.1.dist-info/License.txt
Undo_Redo-1.1.dist-info/METADATA
Undo_Redo-1.1.dist-info/WHEEL
Undo_Redo-1.1.dist-info/top_level.txt
Undo_Redo-1.1.dist-info/RECORD
