Metadata-Version: 2.1
Name: Undo-Redo
Version: 1.1
Summary: Implementation of Undo, Redo
Home-page: https://github.com/abhi1p/UndoRedo
Author: Abhishek Anand
Author-email: abhishekanand2a@gmail.com
License: MIT
Platform: UNKNOWN
